dynasim/__init__.py
dynasim/actuators.py
dynasim/base.py
dynasim/nonlinearities.py
dynasim/simulators.py
dynasim/systems.py
dynasim-0.2.1.0.dist-info/licenses/LICENSE
dynasim-0.2.1.0.dist-info/METADATA
dynasim-0.2.1.0.dist-info/WHEEL
dynasim-0.2.1.0.dist-info/top_level.txt
dynasim-0.2.1.0.dist-info/RECORD
