Metadata-Version: 2.4
Name: dynasim
Version: 0.2.1.0
Summary: Dynamic System Simulators
Author-email: Marcus Haywood-Alexander <mhaywood@ethz.ch>
Project-URL: Homepage, https://github.com/MarcusHA94/dynasim
Classifier: Programming Language :: Python :: 3
Classifier: License :: OSI Approved :: MIT License
Classifier: Operating System :: OS Independent
Requires-Python: >=3.10
License-File: LICENSE
Requires-Dist: numpy
Requires-Dist: scipy
Dynamic: license-file
